nxp_imu/FXAS21002.py
nxp_imu/FXOS8700.py
nxp_imu/I2C.py
nxp_imu/IMU.py
nxp_imu/__init__.py
nxp_imu-0.6.2.dist-info/LICENSE
nxp_imu-0.6.2.dist-info/WHEEL
nxp_imu-0.6.2.dist-info/METADATA
nxp_imu-0.6.2.dist-info/RECORD
