Metadata-Version: 2.1
Name: nxp-imu
Version: 0.6.2
Summary: python library to use the Adafruit NXP 9-Dof IMU
Home-page: https://pypi.org/project/nxp_imu/
License: MIT
Keywords: raspberry,pi,ins,nxp,imu,i2c
Author: walchko
Author-email: walchko@users.noreply.github.com
Requires-Python: >=3.6
Classifier: Development Status :: 4 - Beta
Classifier: Intended Audience :: Developers
Classifier: License :: OSI Approved :: MIT License
Classifier: Operating System :: OS Independent
Classifier: Programming Language :: Python :: 3
Classifier: Programming Language :: Python :: 3.6
Classifier: Programming Language :: Python :: 3.7
Classifier: Programming Language :: Python :: 3.8
Classifier: Topic :: Software Development :: Libraries
Classifier: Topic :: Software Development :: Libraries :: Application Frameworks
Classifier: Topic :: Software Development :: Libraries :: Python Modules
Requires-Dist: importlib-metadata
Requires-Dist: smbus2
Project-URL: Repository, https://github.com/MomsFriendlyRobotCompany/nxp_imu
